{
    "accession": "MITE0000095",
    "quality": "medium",
    "status": "pending",
    "changelog": {
        "releases": [
            {
                "version": "1.0",
                "date": "2024-07-30",
                "entries": [
                    {
                        "contributors": [
                            "Z4WHVO6K4QR4NSPFS3BTTXEO",
                            "SDAWYQYFQDDVDNDD7ZO2XI6Z"
                        ],
                        "reviewers": [
                            "AAAAAAAAAAAAAAAAAAAAAAAA"
                        ],
                        "date": "2024-03-19",
                        "comment": "Initial entry."
                    }
                ]
            }
        ]
    },
    "enzyme": {
        "name": "TnmK1",
        "description": "Catalyzes D-ring-forming Michael addition",
        "databaseIds": [
            "genpept:AME18010.1",
            "mibig:BGC0001378"
        ],
        "references": [
            "pubmed:36279548"
        ]
    },
    "reactions": [
        {
            "tailoring": [
                "Cyclization"
            ],
            "reactionSMARTS": {
                "reactionSMARTS": "[#6:33]-[#8:2]-[#6:7]-1=[#6:8]-[#6:9](-[#6:34])=[#6:4]-2-[#6@@H:3](-[#6]=O)-[#6@@H:6]-1[C:15]#[C:14]\\[#6:13]=[#6:12]/[C:11]#[C:10][#6@@H:5]-2-[#7:1]-[c:29]1[c:28][c:27][c:26](-[#8:30])[c:23]2-[#6:22](=[O:31])-[c:19]3[c:18][c:17][c:16][c:21][c:20]3-[#6:25](=[O:32])-[c:24]12>>[#6:33]-[#8:2]-[#6:7]-1=[#6:8]-[#6:9](-[#6:34])=[#6:4]2-[#6@H:5]3-[#7:1]=[#6:29]-4-[#6@H:28](-[#6:27]-[#6:26](=[O:30])-[c:23]5[c:22](-[#8:31])[c:19]6[c:18][c:17][c:16][c:21][c:20]6[c:25](-[#8:32])[c:24]-45)[C@@:3]2([#6]=O)[#6@@H:6]-1[C:15]#[C:14]\\[#6:13]=[#6:12]/[C:11]#[C:10]3 |r,c:5,14,48,77,t:2,42,45|",
                "isIterative": false
            },
            "reactions": [
                {
                    "substrate": "COC1=CC(C)=C2[C@@H](Nc3ccc(O)c4c3C(=O)c3ccccc3C4=O)C#CC=CC#C[C@H]1[C@@H]2C=O",
                    "products": [
                        "COC1=CC(C)=C2[C@@H]3C#CC=CC#C[C@H]1[C@]2(C=O)[C@H]1CC(=O)c2c(c(O)c4ccccc4c2O)C1=N3"
                    ],
                    "isBalanced": true,
                    "isIntermediate": false
                }
            ],
            "evidence": [
                {
                    "evidenceCode": [
                        "In vitro assay",
                        "Site-directed mutagenesis",
                        "Knock-out studies"
                    ],
                    "references": [
                        "pubmed:36279548"
                    ]
                }
            ]
        }
    ]
}