{
    "accession": "MITE0000173",
    "quality": "medium",
    "status": "pending",
    "changelog": {
        "releases": [
            {
                "version": "1.0",
                "date": "2024-07-30",
                "entries": [
                    {
                        "contributors": [
                            "ZF6B6VBOHAZ5KYONQR36C2NB"
                        ],
                        "reviewers": [
                            "AAAAAAAAAAAAAAAAAAAAAAAA"
                        ],
                        "date": "2024-05-14",
                        "comment": "Initial entry."
                    }
                ]
            }
        ]
    },
    "enzyme": {
        "name": "embB",
        "description": "Cytochrome P450 installing crosslink",
        "references": [
            "doi:10.1101/2023.11.03.565440"
        ],
        "databaseIds": {
            "genpept": "MYS84939.1",
            "mibig": "new658"
        }
    },
    "reactions": [
        {
            "tailoring": [
                "Biaryl bond formation"
            ],
            "reactionSMARTS": {
                "reactionSMARTS": "[#6]-[#6]-[#6@H](-[#6])-[#6@H](-[#7]-[#6](=O)-[#6@H](-[#6]-[#6]-1=[#6]-[#6]=[#6]-[#6]=[#6]-1)-[#7]-[#6](=O)-[#6@@H](-[#7])-[#6]-[#6]-1=[#6]-[#7]-[#6]-2=[#6]-1-[#6]=[#6]-[#6]=[#6]-2)-[#6](=O)-[#7]-[#6@@H](-[#6]-[#6]-1=[#6]-[#7]-[#6]-2=[#6]-1-[#6]=[#6]-[#6]=[#6]-2)-[#6](-[#8])=O>>[#6]-[#6]-[#6@H](-[#6])-[#6@@H]-1-[#7]-[#6](=O)-[#6@H](-[#6]-[#6]-2=[#6]-[#6]=[#6]-[#6]=[#6]-2)-[#7]-[#6](=O)-[#6@@H](-[#7])-[#6]-[#6]-2=[#6]-[#7]-[#6]-3=[#6]-2-[#6]=[#6]-[#6]=[#6]-3-[#7@@]-2-[#6]=[#6](-[#6]-[#6@H](-[#7]-[#6]-1=O)-[#6](-[#8])=O)-[#6]-1=[#6]-2-[#6]=[#6]-[#6]=[#6]-1",
                "isIterative": false
            },
            "reactions": [
                {
                    "substrate": "CC[C@H](C)[C@H](NC(=O)[C@H](Cc1ccccc1)NC(=O)[C@@H](N)Cc1c[nH]c2ccccc12)C(=O)N[C@@H](Cc1c[nH]c2ccccc12)C(=O)O",
                    "products": [
                        "CC[C@H](C)[C@@H]1NC(=O)[C@H](Cc2ccccc2)NC(=O)[C@@H](N)Cc2c[nH]c3c(cccc23)-n2cc(c3ccccc32)C[C@@H](C(=O)O)NC1=O"
                    ],
                    "isBalanced": false,
                    "isIntermediate": false
                }
            ],
            "evidence": [
                {
                    "evidenceCode": [
                        "Heterologous expression"
                    ],
                    "references": [
                        "doi:10.1101/2023.11.03.565440"
                    ]
                }
            ]
        }
    ]
}